leetcode_py/__init__.py
leetcode_py/cli/__init__.py
leetcode_py/cli/commands/__init__.py
leetcode_py/cli/commands/gen.py
leetcode_py/cli/commands/list.py
leetcode_py/cli/commands/scrape.py
leetcode_py/cli/main.py
leetcode_py/cli/resources/leetcode/cookiecutter.json
leetcode_py/cli/resources/leetcode/json/problems/accounts_merge.json
leetcode_py/cli/resources/leetcode/json/problems/add_binary.json
leetcode_py/cli/resources/leetcode/json/problems/add_two_numbers.json
leetcode_py/cli/resources/leetcode/json/problems/alien_dictionary.json
leetcode_py/cli/resources/leetcode/json/problems/balanced_binary_tree.json
leetcode_py/cli/resources/leetcode/json/problems/basic_calculator.json
leetcode_py/cli/resources/leetcode/json/problems/best_time_to_buy_and_sell_stock.json
leetcode_py/cli/resources/leetcode/json/problems/binary_search.json
leetcode_py/cli/resources/leetcode/json/problems/binary_tree_inorder_traversal.json
leetcode_py/cli/resources/leetcode/json/problems/binary_tree_level_order_traversal.json
leetcode_py/cli/resources/leetcode/json/problems/binary_tree_maximum_path_sum.json
leetcode_py/cli/resources/leetcode/json/problems/binary_tree_postorder_traversal.json
leetcode_py/cli/resources/leetcode/json/problems/binary_tree_preorder_traversal.json
leetcode_py/cli/resources/leetcode/json/problems/binary_tree_right_side_view.json
leetcode_py/cli/resources/leetcode/json/problems/climbing_stairs.json
leetcode_py/cli/resources/leetcode/json/problems/clone_graph.json
leetcode_py/cli/resources/leetcode/json/problems/coin_change.json
leetcode_py/cli/resources/leetcode/json/problems/combination_sum.json
leetcode_py/cli/resources/leetcode/json/problems/construct_binary_tree_from_preorder_and_inorder_traversal.json
leetcode_py/cli/resources/leetcode/json/problems/container_with_most_water.json
leetcode_py/cli/resources/leetcode/json/problems/contains_duplicate.json
leetcode_py/cli/resources/leetcode/json/problems/contiguous_array.json
leetcode_py_sdk-0.40.0.dist-info/WHEEL
leetcode_py_sdk-0.40.0.dist-info/entry_points.txt
leetcode_py_sdk-0.40.0.dist-info/METADATA
leetcode_py_sdk-0.40.0.dist-info/RECORD
