Metadata-Version: 2.3
Name: leetcode-py-sdk
Version: 0.40.0
Summary: Modern Python LeetCode practice environment with automated problem generation, beautiful data structure visualizations, and comprehensive testing
Keywords: algorithms,coding-practice,data-structures,interview-prep,leetcode
Author: Wisaroot Lertthaweedech
Author-email: Wisaroot Lertthaweedech <l.wisaroot@gmail.com>
License: Apache-2.0
Classifier: Development Status :: 4 - Beta
Classifier: Intended Audience :: Developers
Classifier: Intended Audience :: Education
Classifier: License :: OSI Approved :: Apache Software License
Classifier: Programming Language :: Python :: 3
Classifier: Programming Language :: Python :: 3.10
Classifier: Programming Language :: Python :: 3.11
Classifier: Programming Language :: Python :: 3.12
Classifier: Programming Language :: Python :: 3.13
Classifier: Programming Language :: Python :: 3.14
Classifier: Topic :: Education
Classifier: Topic :: Software Development :: Libraries :: Python Modules
Requires-Dist: anytree>=2.13.0
Requires-Dist: bakefile[lib]>=0.0.8
Requires-Dist: cookiecutter>=2.6.0
Requires-Dist: graphviz>=0.21
Requires-Dist: json5>=0.13.0
Requires-Dist: loguru>=0.7.3
Requires-Dist: requests>=2.32.5
Requires-Dist: rich>=14.1.0
Requires-Dist: ruff>=0.14.0
Requires-Dist: ty>=0.0.13
Requires-Dist: typer>=0.21.0
Requires-Python: >=3.10
Project-URL: Homepage, https://github.com/wislertt/leetcode-py
Project-URL: Repository, https://github.com/wislertt/leetcode-py
